kladml/__init__.py
kladml/_version.py
kladml/exceptions.py
kladml/tasks.py
kladml/validator.py
kladml/backends/__init__.py
kladml/backends/console_publisher.py
kladml/backends/local_metadata.py
kladml/backends/local_storage.py
kladml/backends/local_tracker.py
kladml/cli/__init__.py
kladml/cli/compare.py
kladml/cli/evaluate.py
kladml/cli/experiments.py
kladml/cli/export.py
kladml/cli/family.py
kladml/cli/init.py
kladml/cli/main.py
kladml/cli/process.py
kladml/cli/projects.py
kladml/cli/registry.py
kladml/cli/run.py
kladml/cli/tune.py
kladml/cli/commands/config.py
kladml/cli/commands/data/__init__.py
kladml/cli/commands/data/core.py
kladml/cli/commands/data/inspect.py
kladml/cli/commands/data/utils.py
kladml/cli/commands/train/__init__.py
kladml/cli/commands/train/core.py
kladml/cli/commands/train/utils.py
kladml/config/__init__.py
kladml/config/logging.py
kladml/config/schema.py
kladml/config/settings.py
kladml/data/__init__.py
kladml/data/converter.py
kladml/data/datamodule.py
kladml/data/defaults.py
kladml/data/hdf5_dataset.py
kladml/data/pipeline.py
kladml/data/preprocessor.py
kladml/data/components/__init__.py
kladml/data/components/cleaning.py
kladml/data/components/io.py
kladml/data/components/resampling.py
kladml/data/components/splitting.py
kladml/data/parsers/__init__.py
kladml/data/parsers/j1939.py
kladml/db/__init__.py
kladml/db/models.py
kladml/db/session.py
kladml/evaluation/__init__.py
kladml/evaluation/base.py
kladml/evaluation/probabilistic.py
kladml/evaluation/registry.py
kladml/evaluation/classification/__init__.py
kladml/evaluation/classification/evaluator.py
kladml/evaluation/regression/__init__.py
kladml/evaluation/regression/evaluator.py
kladml/evaluation/timeseries/__init__.py
kladml/exporters/__init__.py
kladml/exporters/onnx.py
kladml/exporters/registry.py
kladml/exporters/torchscript.py
kladml/interfaces/__init__.py
kladml/interfaces/config.py
kladml/interfaces/exporter.py
kladml/interfaces/metadata.py
kladml/interfaces/publisher.py
kladml-0.13.1.dist-info/licenses/LICENSE
kladml-0.13.1.dist-info/METADATA
kladml-0.13.1.dist-info/WHEEL
kladml-0.13.1.dist-info/entry_points.txt
kladml-0.13.1.dist-info/top_level.txt
kladml-0.13.1.dist-info/RECORD
