Metadata-Version: 2.4
Name: kladml
Version: 0.13.1
Summary: KladML SDK - Enterprise-grade MLOps toolkit
Author-email: KladML Team <marcello@netcaring.com>
License-Expression: MIT
Project-URL: Homepage, https://github.com/kladml/kladml
Project-URL: Documentation, https://docs.klad.ml
Project-URL: Repository, https://github.com/kladml/kladml.git
Project-URL: Issues, https://github.com/kladml/kladml/issues
Classifier: Development Status :: 3 - Alpha
Classifier: Intended Audience :: Developers
Classifier: Intended Audience :: Science/Research
Classifier: Programming Language :: Python :: 3
Classifier: Programming Language :: Python :: 3.10
Classifier: Programming Language :: Python :: 3.11
Classifier: Programming Language :: Python :: 3.12
Classifier: Topic :: Scientific/Engineering :: Artificial Intelligence
Requires-Python: <3.14,>=3.10
License-File: LICENSE
Requires-Dist: pyyaml>=6.0
Requires-Dist: pydantic>=2.0.0
Requires-Dist: pydantic-settings>=2.0.0
Requires-Dist: sqlalchemy>=2.0.0
Requires-Dist: sqlmodel>=0.0.16
Requires-Dist: typer[all]>=0.9.0
Requires-Dist: rich>=13.0.0
Requires-Dist: accelerate>=0.24.0
Requires-Dist: platformdirs>=3.0.0
Requires-Dist: loguru>=0.7.0
Provides-Extra: train
Requires-Dist: torch>=2.0.0; extra == "train"
Requires-Dist: numpy>=1.21.0; extra == "train"
Requires-Dist: onnx>=1.14.0; extra == "train"
Requires-Dist: onnxruntime>=1.15.0; extra == "train"
Requires-Dist: h5py>=3.0.0; extra == "train"
Requires-Dist: onnxscript>=0.1.0; extra == "train"
Requires-Dist: matplotlib>=3.7.0; extra == "train"
Requires-Dist: torchmetrics>=1.0.0; extra == "train"
Requires-Dist: polars>=0.19.0; extra == "train"
Requires-Dist: pyarrow>=14.0.0; extra == "train"
Provides-Extra: tracking
Requires-Dist: mlflow<3.0.0,>=2.14.0; extra == "tracking"
Provides-Extra: dev
Requires-Dist: pytest>=7.0; extra == "dev"
Requires-Dist: pytest-cov>=4.0; extra == "dev"
Requires-Dist: ruff>=0.1.0; extra == "dev"
Requires-Dist: build>=1.0.0; extra == "dev"
Requires-Dist: twine>=4.0.0; extra == "dev"
Provides-Extra: all
Requires-Dist: kladml[dev,tracking,train]; extra == "all"
Dynamic: license-file
